my_phone_validator/__init__.py
my_phone_validator/validator.py
my_phone_validator-0.1.0.dist-info/METADATA
my_phone_validator-0.1.0.dist-info/WHEEL
my_phone_validator-0.1.0.dist-info/RECORD
