Metadata-Version: 2.1
Name: my-phone-validator
Version: 0.1.0
Summary: 
Author: deshana.parikh
Author-email: deshana.parikh@crestdatasys.com
Requires-Python: >=3.12,<4.0
Classifier: Programming Language :: Python :: 3
Classifier: Programming Language :: Python :: 3.12
Requires-Dist: requests (>=2.31.0,<3.0.0)
